BODSDataExtractor/ATCO_code_to_LA_lookup.csv
BODSDataExtractor/__init__.py
BODSDataExtractor/classes.py
BODSDataExtractor/example.py
BODSDataExtractor/extractor.py
BODSDataExtractor/otc_db_download.py
BODSDataExtractor-1.2.1.dist-info/LICENCE
BODSDataExtractor-1.2.1.dist-info/METADATA
BODSDataExtractor-1.2.1.dist-info/WHEEL
BODSDataExtractor-1.2.1.dist-info/top_level.txt
BODSDataExtractor-1.2.1.dist-info/RECORD
