Metadata-Version: 2.1
Name: BODSDataExtractor
Version: 1.2.1
Summary: This project was created to lower the barrier to entry for analysis of UK Bus Open Data. It facilitates the fetching and extraction of clean data, currently focussed on Timetables, into tables to be used for analysis or your own projects.
Author-email: "Ali Partner, Spencer Brittain" <bodshelpdesk@kpmg.co.uk>
Project-URL: Homepage, https://github.com/department-for-transport-BODS/bods-data-extractor
Classifier: Programming Language :: Python :: 3
Classifier: License :: OSI Approved :: MIT License
Classifier: Operating System :: OS Independent
Requires-Python: >=3.8
License-File: LICENCE
Requires-Dist: pandas (>=1.4.2)
Requires-Dist: bods-client (>=0.11.0)
Requires-Dist: protobuf (==3.20)
Requires-Dist: lxml (==4.9.1)
Requires-Dist: xmltodict (==0.13.0)
Requires-Dist: shapely (>=1.8.5)
Requires-Dist: geopandas (>=0.12.1)
Requires-Dist: plotly (<=5.13.1)
Requires-Dist: dacite (>=1.8.1)
